d_save_last-0.1.2.data/scripts/d-save-last
docker_save_last/__init__.py
docker_save_last/command.py
docker_save_last/main.py
d_save_last-0.1.2.dist-info/LICENSE
d_save_last-0.1.2.dist-info/METADATA
d_save_last-0.1.2.dist-info/WHEEL
d_save_last-0.1.2.dist-info/top_level.txt
d_save_last-0.1.2.dist-info/RECORD
