Metadata-Version: 2.1
Name: d-save-last
Version: 0.1.2
Summary: A command line utility effectively replicating `docker save` except that it will only save the LAST layer of the image in the output archive.
Home-page: https://github.com/brthor/docker-save-last-layer
Author: Bryan Thornbury
Author-email: author@example.com
License: MIT
Platform: UNKNOWN
Classifier: Programming Language :: Python :: 2.7
Classifier: Operating System :: OS Independent
Classifier: Intended Audience :: Developers
Classifier: Intended Audience :: System Administrators
Classifier: Topic :: Software Development :: Build Tools
Classifier: Topic :: Utilities
